backports.socketpair-3.5.0.4-py3.6-nspkg.pth
backports/socketpair/__init__.py
backports.socketpair-3.5.0.4.dist-info/DESCRIPTION.rst
backports.socketpair-3.5.0.4.dist-info/METADATA
backports.socketpair-3.5.0.4.dist-info/RECORD
backports.socketpair-3.5.0.4.dist-info/WHEEL
backports.socketpair-3.5.0.4.dist-info/metadata.json
backports.socketpair-3.5.0.4.dist-info/namespace_packages.txt
backports.socketpair-3.5.0.4.dist-info/top_level.txt
