Metadata-Version: 2.0
Name: backports.socketpair
Version: 3.5.0.4
Summary: Python 2 support for socket.socketpair() on Windows
Home-page: https://github.com/mhils/backports.socketpair
Author: Maximilian Hils
Author-email: socketpair@maximilianhils.com
License: Python Software Foundation License
Keywords: socket socketpair backport
Platform: UNKNOWN
Classifier: Development Status :: 5 - Production/Stable
Classifier: License :: OSI Approved :: Python Software Foundation License
Classifier: Intended Audience :: Developers
Classifier: Programming Language :: Python :: 2
Classifier: Programming Language :: Python :: 2.7
Classifier: Programming Language :: Python :: 3
Classifier: Programming Language :: Python :: 3.2
Classifier: Programming Language :: Python :: 3.3
Classifier: Programming Language :: Python :: 3.4
